depayco/__init__.py
depayco/admin.py
depayco/apps.py
depayco/models.py
depayco/tests.py
depayco/urls.py
depayco/views.py
depayco/actions/__init__.py
depayco/actions/credit_cards.py
depayco/actions/customers.py
depayco/actions/plans.py
depayco/actions/subscriptions.py
depayco/addons/__init__.py
depayco/addons/choices.py
depayco/addons/decorators.py
depayco/addons/forms.py
depayco/management/__init__.py
depayco/management/commands/__init__.py
depayco/management/commands/sync_plans.py
depayco/management/commands/sync_subscriptions.py
depayco/migrations/0001_initial.py
depayco/migrations/0002_subscription_is_active.py
depayco/migrations/0003_auto_20181011_1421.py
depayco/migrations/0004_subscription_current_period_end.py
depayco/migrations/0005_auto_20181011_1620.py
depayco/migrations/0006_auto_20181011_1651.py
depayco/migrations/__init__.py
depayco-1.1.1.dist-info/LICENSE
depayco-1.1.1.dist-info/METADATA
depayco-1.1.1.dist-info/WHEEL
depayco-1.1.1.dist-info/top_level.txt
depayco-1.1.1.dist-info/RECORD
