Metadata-Version: 2.1
Name: depayco
Version: 1.1.1
Summary: Django integration with ePayco (epayco.co)
Home-page: https://github.com/ma1onso/depayco
Author: Alonso
Author-email: alons45@gmail.com
License: GPL
Platform: UNKNOWN
Classifier: Programming Language :: Python :: 3
Classifier: License :: OSI Approved :: GNU General Public License v3 (GPLv3)
Classifier: Operating System :: OS Independent
Classifier: Development Status :: 5 - Production/Stable
Classifier: Intended Audience :: Developers
Classifier: Framework :: Django
Classifier: Environment :: Web Environment
Requires-Python: >=3.6
Requires-Dist: pyepayco (==1.0.0)
Requires-Dist: requests (>=2.4.3)
Requires-Dist: pycrypto (>=2.3)
